embeddingbuddy/__init__.py
embeddingbuddy/app.py
embeddingbuddy/cli.py
embeddingbuddy/wsgi.py
embeddingbuddy/assets/custom.css
embeddingbuddy/assets/embeddings.js
embeddingbuddy/assets/fontawesome.css
embeddingbuddy/assets/package.json
embeddingbuddy/assets/sample-txt.md
embeddingbuddy/assets/transformers-loader.js
embeddingbuddy/assets/fontawesome/LICENSE.txt
embeddingbuddy/assets/fontawesome/css/all.min.css
embeddingbuddy/assets/fontawesome/webfonts/fa-brands-400.ttf
embeddingbuddy/assets/fontawesome/webfonts/fa-brands-400.woff2
embeddingbuddy/assets/fontawesome/webfonts/fa-regular-400.ttf
embeddingbuddy/assets/fontawesome/webfonts/fa-regular-400.woff2
embeddingbuddy/assets/fontawesome/webfonts/fa-solid-900.ttf
embeddingbuddy/assets/fontawesome/webfonts/fa-solid-900.woff2
embeddingbuddy/assets/fontawesome/webfonts/fa-v4compatibility.ttf
embeddingbuddy/assets/fontawesome/webfonts/fa-v4compatibility.woff2
embeddingbuddy/config/__init__.py
embeddingbuddy/config/settings.py
embeddingbuddy/data/__init__.py
embeddingbuddy/data/parser.py
embeddingbuddy/data/processor.py
embeddingbuddy/data/sources/__init__.py
embeddingbuddy/data/sources/opensearch.py
embeddingbuddy/models/__init__.py
embeddingbuddy/models/field_mapper.py
embeddingbuddy/models/reducers.py
embeddingbuddy/models/schemas.py
embeddingbuddy/ui/__init__.py
embeddingbuddy/ui/layout.py
embeddingbuddy/ui/callbacks/__init__.py
embeddingbuddy/ui/callbacks/data_processing.py
embeddingbuddy/ui/callbacks/interactions.py
embeddingbuddy/ui/callbacks/visualization.py
embeddingbuddy/ui/components/__init__.py
embeddingbuddy/ui/components/about.py
embeddingbuddy/ui/components/datasource.py
embeddingbuddy/ui/components/sidebar.py
embeddingbuddy/ui/components/textinput.py
embeddingbuddy/ui/components/upload.py
embeddingbuddy/utils/__init__.py
embeddingbuddy/visualization/__init__.py
embeddingbuddy/visualization/colors.py
embeddingbuddy/visualization/plots.py
embeddingbuddy-0.8.3.dist-info/licenses/LICENSE
embeddingbuddy-0.8.3.dist-info/METADATA
embeddingbuddy-0.8.3.dist-info/WHEEL
embeddingbuddy-0.8.3.dist-info/entry_points.txt
embeddingbuddy-0.8.3.dist-info/top_level.txt
embeddingbuddy-0.8.3.dist-info/RECORD
