Metadata-Version: 2.4
Name: embeddingbuddy
Version: 0.8.3
Summary: A Python Dash application for interactive exploration and visualization of embedding vectors through dimensionality reduction techniques.
Requires-Python: >=3.11
License-File: LICENSE
Requires-Dist: dash>=2.17.1
Requires-Dist: plotly>=5.17.0
Requires-Dist: pandas>=2.1.4
Requires-Dist: numpy>=1.24.4
Requires-Dist: scikit-learn>=1.3.2
Requires-Dist: dash-bootstrap-components>=1.5.0
Requires-Dist: umap-learn>=0.5.8
Requires-Dist: openTSNE>=1.0.0
Requires-Dist: mypy>=1.17.1
Requires-Dist: opensearch-py>=3.0.0
Provides-Extra: test
Requires-Dist: pytest>=8.4.1; extra == "test"
Requires-Dist: pytest-cov>=4.1.0; extra == "test"
Provides-Extra: lint
Requires-Dist: ruff>=0.1.0; extra == "lint"
Requires-Dist: mypy>=1.5.0; extra == "lint"
Provides-Extra: security
Requires-Dist: bandit[toml]>=1.7.5; extra == "security"
Requires-Dist: safety>=2.3.0; extra == "security"
Requires-Dist: pip-audit>=2.6.0; extra == "security"
Provides-Extra: prod
Requires-Dist: gunicorn>=21.2.0; extra == "prod"
Provides-Extra: dev
Requires-Dist: embeddingbuddy[lint,security,test]; extra == "dev"
Provides-Extra: all
Requires-Dist: embeddingbuddy[lint,prod,security,test]; extra == "all"
Dynamic: license-file
